.coveragerc
.gitignore
.isort.cfg
.pre-commit-config.yaml
.travis.yml
AUTHORS.rst
CHANGELOG.rst
LICENSE.txt
Makefile
README.rst
pyproject.toml
requirements.txt
setup.cfg
setup.py
tox.ini
docs/.buildinfo
docs/.nojekyll
docs/authors.html
docs/census.html
docs/census_files.html
docs/changelog.html
docs/genindex.html
docs/index.html
docs/license.html
docs/objects.inv
docs/py-modindex.html
docs/search.html
docs/searchindex.js
docs/_modules/index.html
docs/_modules/publicdata/census/appurl.html
docs/_modules/publicdata/census/bib.html
docs/_modules/publicdata/census/dataframe.html
docs/_modules/publicdata/census/dimensions.html
docs/_modules/publicdata/census/exceptions.html
docs/_modules/publicdata/census/files.html
docs/_modules/publicdata/census/func.html
docs/_modules/publicdata/census/geocode.html
docs/_modules/publicdata/census/groupby.html
docs/_modules/publicdata/census/series.html
docs/_modules/publicdata/census/test.html
docs/_modules/publicdata/census/util.html
docs/_modules/publicdata/census/api/censusapi.html
docs/_modules/publicdata/census/api/generator.html
docs/_modules/publicdata/census/api/url.html
docs/_modules/publicdata/census/api/test/test_censusapi.html
docs/_modules/publicdata/census/censusreporter/exceptions.html
docs/_modules/publicdata/census/censusreporter/generator.html
docs/_modules/publicdata/census/censusreporter/jsonurl.html
docs/_modules/publicdata/census/censusreporter/url.html
docs/_modules/publicdata/census/censusreporter/test/test_censusreporter.html
docs/_modules/publicdata/census/files/appurl.html
docs/_modules/publicdata/census/files/generators.html
docs/_modules/publicdata/census/files/metafiles.html
docs/_modules/publicdata/census/files/url_templates.html
docs/_modules/publicdata/census/test/files/test_appurls.html
docs/_modules/publicdata/census/test/files/test_generators.html
docs/_modules/publicdata/census/test/files/test_issues.html
docs/_modules/publicdata/census/test/files/test_meta.html
src/publicdata_census.egg-info/PKG-INFO
src/publicdata_census.egg-info/SOURCES.txt
src/publicdata_census.egg-info/dependency_links.txt
src/publicdata_census.egg-info/entry_points.txt
src/publicdata_census.egg-info/not-zip-safe
src/publicdata_census.egg-info/requires.txt
src/publicdata_census.egg-info/top_level.txt
