Metadata-Version: 2.1
Name: publicdata-census
Version: 0.0.5
Summary: Row generators and URLs for working with census data
Home-page: https://github.com/Metatab/publicdata_census
Author: Eric Busboom
Author-email: eric@civicknowledge.com
License: mit
Project-URL: Documentation, https://github.com/Metatab/publicdata_census
Platform: any
Classifier: Development Status :: 4 - Beta
Classifier: Programming Language :: Python
Provides-Extra: testing
